pykle_serial/__init__.py
pykle_serial/serial.py
pykle_serial-0.1.1.dist-info/LICENSE
pykle_serial-0.1.1.dist-info/METADATA
pykle_serial-0.1.1.dist-info/WHEEL
pykle_serial-0.1.1.dist-info/top_level.txt
pykle_serial-0.1.1.dist-info/RECORD
