Metadata-Version: 2.2
Name: pykle-serial
Version: 0.1.1
Summary: A Python library for parsing the serialized format used on keyboard-layout-editor.com (KLE).
Author-email: Hajime Nakazato <hajime@kaoriha.org>
License: MIT License
Project-URL: Repository, https://github.com/hajimen/pykle_serial.git
Project-URL: Bug Tracker, https://github.com/hajimen/pykle_serial/issues
Project-URL: Changelog, https://github.com/hajimen/pykle_serial/blob/master/CHANGELOG.md
Keywords: keyboard-layout-editor,KLE
Classifier: Development Status :: 4 - Beta
Classifier: Intended Audience :: Developers
Classifier: Operating System :: OS Independent
Classifier: Programming Language :: Python
Classifier: Programming Language :: Python :: 3.8
Classifier: Programming Language :: Python :: 3.9
Classifier: Programming Language :: Python :: 3.10
Classifier: Programming Language :: Python :: 3.11
Classifier: Programming Language :: Python :: 3.12
Classifier: Programming Language :: Python :: 3.13
Classifier: Topic :: Software Development :: Libraries :: Python Modules
Requires-Python: >=3.8
License-File: LICENSE
Requires-Dist: json5>=0.9.5
